yit/__init__.py
yit/__main__.py
yit/main.py
yit-0.0.1.dist-info/LICENSE
yit-0.0.1.dist-info/METADATA
yit-0.0.1.dist-info/WHEEL
yit-0.0.1.dist-info/entry_points.txt
yit-0.0.1.dist-info/top_level.txt
yit-0.0.1.dist-info/RECORD
